jbs/__init__.py
jbs/ir.py
jbs/ml.py
jbs/quotations.py
tests/__init__.py
tests/test_jbs_ir.py
tests/test_jbs_nlp.py
tests/test_ml.py
tests/test_quotationdetection.py
tests/test_quotations.py
tests/test_textanalysis.py
jbs_utils-0.0.4.dist-info/LICENSE
jbs_utils-0.0.4.dist-info/METADATA
jbs_utils-0.0.4.dist-info/WHEEL
jbs_utils-0.0.4.dist-info/top_level.txt
jbs_utils-0.0.4.dist-info/RECORD
